Workbook

Sheet Summary
A1: Location | B1: IRR (%) | C1: NPV ($) | D1: Annual Worth ($) | E1: Payback Period (Years)
A2: Charleston | B2: =IRR('Charleston, SC'!J2:J32)*100 -> 4.4779604 | C2: =NPV(0.1,'Charleston, SC'!J2:J32) -> -61121812 | D2: =NPV(0.1,'Charleston, SC'!J2:J32)*(0.1*(1+0.1)^30)/((1+0.1)^30-1) -> -6483755.9 | E2: 16
A3: Wichita | B3: =IRR('Wichita, KS'!J2:J32)*100 -> 23.083106 | C3: =NPV(0.1,'Wichita, KS'!J2:J32) -> 1.6871505e+08 | D3: =NPV(0.1,'Wichita, KS'!J2:J32)*(0.1*(1+0.1)^30)/((1+0.1)^30-1) -> 17897166 | E3: 5
A6: Recommendation: Among the 2 recommended locations, Wichita, Kansas would be the better option to start a new facility for Boeing Company
A7: Workbook uploaded in Google Sheets for easy access.
A8: Workbook Link

Sheet Assumptions
A1: Assumptions | B1: Charleston, SC | C1: Wichita, KS
A2: Estimated CAPEX ($) - Facility Construction, Setup and Miscellaneous Cost | B2: 165000000 | C2: 160000000
A3: Annual Revenue ($) (Projected Revenue = 0.9% of $77.8B) | B3: 693000000 | C3: 693000000
A4: Labor Cost per Employee | B4: 85000 | C4: 80000
A5: Labor Force | B5: 7000 | C5: 7000
A6: Total Labor Cost ($) | B6: 595000000 | C6: 560000000
A7: O&M Cost ($) | B7: 86625000 | C7: 86625000
A8: Tax Rate | B8: 0.26 | C8: 0.25
A9: Facility Size (sq ft) | B9: 1.5 million | C9: 1.5 million
A10: Depreciation Method | B10: MACRS 39-year | C10: MACRS 39-year
A11: Project Life | B11: 30 Years | C11: 30 Years
A12: MARR | B12: 0.1 | C12: 0.1

Sheet Depreciation Rate (MACRS)
A1: Year | B1: MACRS %
A2: 1 | B2: 0.02564
A3: 2 | B3: 0.06513
A4: 3 | B4: 0.06179
A5: 4 | B5: 0.05901
A6: 5 | B6: 0.05635
A7: 6 | B7: 0.05376
A8: 7 | B8: 0.05125
A9: 8 | B9: 0.04881
A10: 9 | B10: 0.04644
A11: 10 | B11: 0.04413
A12: 11 | B12: 0.04189
A13: 12 | B13: 0.03972
... A40: 39 | B40: 0.00548

Sheet Charleston, SC
A1: Year | B1: Depreciation | C1: Revenue | D1: Labor Cost | E1: O&M Cost | F1: EBIT | G1: Taxable Income | H1: Tax | I1: Net Income | J1: CFAT | K1: Cumulative CFAT
A2: 0 | B2: 0 | C2: 0 | D2: 0 | E2: 0 | F2: 0 | G2: 0 | H2: 0 | I2: 0 | J2: -165000000 | K2: -165000000
A3: 1 | B3: =Assumptions!B2*0.06513 -> 10746450 | C3: 693000000 | D3: 595000000 | E3: 86625000 | F3: =C3-D3-E3 -> 11375000 | G3: =F3-B3 -> 628550 | H3: =MAX(0,G3*0.26) -> 163423 | I3: =G3-H3 -> 465127 | J3: =I3+B3 -> 11211577 | K3: =K2+J3 -> -153788423
A4: 2 | B4: =Assumptions!B2*0.06179 -> 10195350 | C4: 693000000 | D4: 595000000 | E4: 86625000 | F4: =C4-D4-E4 -> 11375000 | G4: =F4-B4 -> 1179650 | H4: =MAX(0,G4*0.26) -> 306709 | I4: =G4-H4 -> 872941 | J4: =I4+B4 -> 11068291 | K4: =K3+J4 -> -142720132
A5: 3 | B5: =Assumptions!B2*0.05901 -> 9736650 | C5: 693000000 | D5: 595000000 | E5: 86625000 | F5: =C5-D5-E5 -> 11375000 | G5: =F5-B5 -> 1638350 | H5: =MAX(0,G5*0.26) -> 425971 | I5: =G5-H5 -> 1212379 | J5: =I5+B5 -> 10949029 | K5: =K4+J5 -> -131771103
A6: 4 | B6: =Assumptions!B2*0.05635 -> 9297750 | C6: 693000000 | D6: 595000000 | E6: 86625000 | F6: =C6-D6-E6 -> 11375000 | G6: =F6-B6 -> 2077250 | H6: =MAX(0,G6*0.26) -> 540085 | I6: =G6-H6 -> 1537165 | J6: =I6+B6 -> 10834915 | K6: =K5+J6 -> -120936188
A7: 5 | B7: =Assumptions!B2*0.05376 -> 8870400 | C7: 693000000 | D7: 595000000 | E7: 86625000 | F7: =C7-D7-E7 -> 11375000 | G7: =F7-B7 -> 2504600 | H7: =MAX(0,G7*0.26) -> 651196 | I7: =G7-H7 -> 1853404 | J7: =I7+B7 -> 10723804 | K7: =K6+J7 -> -110212384
A8: 6 | B8: =Assumptions!B2*0.05125 -> 8456250 | C8: 693000000 | D8: 595000000 | E8: 86625000 | F8: =C8-D8-E8 -> 11375000 | G8: =F8-B8 -> 2918750 | H8: =MAX(0,G8*0.26) -> 758875 | I8: =G8-H8 -> 2159875 | J8: =I8+B8 -> 10616125 | K8: =K7+J8 -> -99596259
A9: 7 | B9: =Assumptions!B2*0.04881 -> 8053650 | C9: 693000000 | D9: 595000000 | E9: 86625000 | F9: =C9-D9-E9 -> 11375000 | G9: =F9-B9 -> 3321350 | H9: =MAX(0,G9*0.26) -> 863551 | I9: =G9-H9 -> 2457799 | J9: =I9+B9 -> 10511449 | K9: =K8+J9 -> -89084810
A10: 8 | B10: =Assumptions!B2*0.04644 -> 7662600 | C10: 693000000 | D10: 595000000 | E10: 86625000 | F10: =C10-D10-E10 -> 11375000 | G10: =F10-B10 -> 3712400 | H10: =MAX(0,G10*0.26) -> 965224 | I10: =G10-H10 -> 2747176 | J10: =I10+B10 -> 10409776 | K10: =K9+J10 -> -78675034
A11: 9 | B11: =Assumptions!B2*0.04413 -> 7281450 | C11: 693000000 | D11: 595000000 | E11: 86625000 | F11: =C11-D11-E11 -> 11375000 | G11: =F11-B11 -> 4093550 | H11: =MAX(0,G11*0.26) -> 1064323 | I11: =G11-H11 -> 3029227 | J11: =I11+B11 -> 10310677 | K11: =K10+J11 -> -68364357
A12: 10 | B12: =Assumptions!B2*0.04189 -> 6911850 | C12: 693000000 | D12: 595000000 | E12: 86625000 | F12: =C12-D12-E12 -> 11375000 | G12: =F12-B12 -> 4463150 | H12: =MAX(0,G12*0.26) -> 1160419 | I12: =G12-H12 -> 3302731 | J12: =I12+B12 -> 10214581 | K12: =K11+J12 -> -58149776
A13: 11 | B13: =Assumptions!B2*0.03972 -> 6553800 | C13: 693000000 | D13: 595000000 | E13: 86625000 | F13: =C13-D13-E13 -> 11375000 | G13: =F13-B13 -> 4821200 | H13: =MAX(0,G13*0.26) -> 1253512 | I13: =G13-H13 -> 3567688 | J13: =I13+B13 -> 10121488 | K13: =K12+J13 -> -48028288
A14: 12 | B14: =Assumptions!B2*0.03762 -> 6207300 | C14: 693000000 | D14: 595000000 | E14: 86625000 | F14: =C14-D14-E14 -> 11375000 | G14: =F14-B14 -> 5167700 | H14: =MAX(0,G14*0.26) -> 1343602 | I14: =G14-H14 -> 3824098 | J14: =I14+B14 -> 10031398 | K14: =K13+J14 -> -37996890
A15: 13 | B15: =Assumptions!B2*0.03558 -> 5870700 | C15: 693000000 | D15: 595000000 | E15: 86625000 | F15: =C15-D15-E15 -> 11375000 | G15: =F15-B15 -> 5504300 | H15: =MAX(0,G15*0.26) -> 1431118 | I15: =G15-H15 -> 4073182 | J15: =I15+B15 -> 9943882 | K15: =K14+J15 -> -28053008
A16: 14 | B16: =Assumptions!B2*0.03361 -> 5545650 | C16: 693000000 | D16: 595000000 | E16: 86625000 | F16: =C16-D16-E16 -> 11375000 | G16: =F16-B16 -> 5829350 | H16: =MAX(0,G16*0.26) -> 1515631 | I16: =G16-H16 -> 4313719 | J16: =I16+B16 -> 9859369 | K16: =K15+J16 -> -18193639
A17: 15 | B17: =Assumptions!B2*0.0317 -> 5230500 | C17: 693000000 | D17: 595000000 | E17: 86625000 | F17: =C17-D17-E17 -> 11375000 | G17: =F17-B17 -> 6144500 | H17: =MAX(0,G17*0.26) -> 1597570 | I17: =G17-H17 -> 4546930 | J17: =I17+B17 -> 9777430 | K17: =K16+J17 -> -8416209
A18: 16 | B18: =Assumptions!B2*0.02986 -> 4926900 | C18: 693000000 | D18: 595000000 | E18: 86625000 | F18: =C18-D18-E18 -> 11375000 | G18: =F18-B18 -> 6448100 | H18: =MAX(0,G18*0.26) -> 1676506 | I18: =G18-H18 -> 4771594 | J18: =I18+B18 -> 9698494 | K18: =K17+J18 -> 1282285
A19: 17 | B19: =Assumptions!B2*0.02808 -> 4633200 | C19: 693000000 | D19: 595000000 | E19: 86625000 | F19: =C19-D19-E19 -> 11375000 | G19: =F19-B19 -> 6741800 | H19: =MAX(0,G19*0.26) -> 1752868 | I19: =G19-H19 -> 4988932 | J19: =I19+B19 -> 9622132 | K19: =K18+J19 -> 10904417
A20: 18 | B20: =Assumptions!B2*0.02637 -> 4351050 | C20: 693000000 | D20: 595000000 | E20: 86625000 | F20: =C20-D20-E20 -> 11375000 | G20: =F20-B20 -> 7023950 | H20: =MAX(0,G20*0.26) -> 1826227 | I20: =G20-H20 -> 5197723 | J20: =I20+B20 -> 9548773 | K20: =K19+J20 -> 20453190
A21: 19 | B21: =Assumptions!B2*0.02472 -> 4078800 | C21: 693000000 | D21: 595000000 | E21: 86625000 | F21: =C21-D21-E21 -> 11375000 | G21: =F21-B21 -> 7296200 | H21: =MAX(0,G21*0.26) -> 1897012 | I21: =G21-H21 -> 5399188 | J21: =I21+B21 -> 9477988 | K21: =K20+J21 -> 29931178
A22: 20 | B22: =Assumptions!B2*0.02314 -> 3818100 | C22: 693000000 | D22: 595000000 | E22: 86625000 | F22: =C22-D22-E22 -> 11375000 | G22: =F22-B22 -> 7556900 | H22: =MAX(0,G22*0.26) -> 1964794 | I22: =G22-H22 -> 5592106 | J22: =I22+B22 -> 9410206 | K22: =K21+J22 -> 39341384
A23: 21 | B23: =Assumptions!B2*0.02162 -> 3567300 | C23: 693000000 | D23: 595000000 | E23: 86625000 | F23: =C23-D23-E23 -> 11375000 | G23: =F23-B23 -> 7807700 | H23: =MAX(0,G23*0.26) -> 2030002 | I23: =G23-H23 -> 5777698 | J23: =I23+B23 -> 9344998 | K23: =K22+J23 -> 48686382
A24: 22 | B24: =Assumptions!B2*0.02017 -> 3328050 | C24: 693000000 | D24: 595000000 | E24: 86625000 | F24: =C24-D24-E24 -> 11375000 | G24: =F24-B24 -> 8046950 | H24: =MAX(0,G24*0.26) -> 2092207 | I24: =G24-H24 -> 5954743 | J24: =I24+B24 -> 9282793 | K24: =K23+J24 -> 57969175
A25: 23 | B25: =Assumptions!B2*0.01878 -> 3098700 | C25: 693000000 | D25: 595000000 | E25: 86625000 | F25: =C25-D25-E25 -> 11375000 | G25: =F25-B25 -> 8276300 | H25: =MAX(0,G25*0.26) -> 2151838 | I25: =G25-H25 -> 6124462 | J25: =I25+B25 -> 9223162 | K25: =K24+J25 -> 67192337
A26: 24 | B26: =Assumptions!B2*0.01746 -> 2880900 | C26: 693000000 | D26: 595000000 | E26: 86625000 | F26: =C26-D26-E26 -> 11375000 | G26: =F26-B26 -> 8494100 | H26: =MAX(0,G26*0.26) -> 2208466 | I26: =G26-H26 -> 6285634 | J26: =I26+B26 -> 9166534 | K26: =K25+J26 -> 76358871
A27: 25 | B27: =Assumptions!B2*0.0162 -> 2673000 | C27: 693000000 | D27: 595000000 | E27: 86625000 | F27: =C27-D27-E27 -> 11375000 | G27: =F27-B27 -> 8702000 | H27: =MAX(0,G27*0.26) -> 2262520 | I27: =G27-H27 -> 6439480 | J27: =I27+B27 -> 9112480 | K27: =K26+J27 -> 85471351
A28: 26 | B28: =Assumptions!B2*0.015 -> 2475000 | C28: 693000000 | D28: 595000000 | E28: 86625000 | F28: =C28-D28-E28 -> 11375000 | G28: =F28-B28 -> 8900000 | H28: =MAX(0,G28*0.26) -> 2314000 | I28: =G28-H28 -> 6586000 | J28: =I28+B28 -> 9061000 | K28: =K27+J28 -> 94532351
A29: 27 | B29: =Assumptions!B2*0.01387 -> 2288550 | C29: 693000000 | D29: 595000000 | E29: 86625000 | F29: =C29-D29-E29 -> 11375000 | G29: =F29-B29 -> 9086450 | H29: =MAX(0,G29*0.26) -> 2362477 | I29: =G29-H29 -> 6723973 | J29: =I29+B29 -> 9012523 | K29: =K28+J29 -> 103544874
A30: 28 | B30: =Assumptions!B2*0.0128 -> 2112000 | C30: 693000000 | D30: 595000000 | E30: 86625000 | F30: =C30-D30-E30 -> 11375000 | G30: =F30-B30 -> 9263000 | H30: =MAX(0,G30*0.26) -> 2408380 | I30: =G30-H30 -> 6854620 | J30: =I30+B30 -> 8966620 | K30: =K29+J30 -> 112511494
A31: 29 | B31: =Assumptions!B2*0.0118 -> 1947000 | C31: 693000000 | D31: 595000000 | E31: 86625000 | F31: =C31-D31-E31 -> 11375000 | G31: =F31-B31 -> 9428000 | H31: =MAX(0,G31*0.26) -> 2451280 | I31: =G31-H31 -> 6976720 | J31: =I31+B31 -> 8923720 | K31: =K30+J31 -> 121435214
A32: 30 | B32: =Assumptions!B2*0.01086 -> 1791900 | C32: 693000000 | D32: 595000000 | E32: 86625000 | F32: =C32-D32-E32 -> 11375000 | G32: =F32-B32 -> 9583100 | H32: =MAX(0,G32*0.26) -> 2491606 | I32: =G32-H32 -> 7091494 | J32: =I32+B32 -> 8883394 | K32: =K31+J32 -> 130318608

Sheet Wichita, KS
A1: Year | B1: Depreciation | C1: Revenue | D1: Labor Cost | E1: O&M Cost | F1: EBIT | G1: Taxable Income | H1: Tax | I1: Net Income | J1: CFAT | K1: Cumulative CFAT
A2: 0 | B2: 0 | C2: 0 | D2: 0 | E2: 0 | F2: 0 | G2: 0 | H2: 0 | I2: 0 | J2: -160000000 | K2: -160000000
A3: 1 | B3: =Assumptions!B2*0.06513 -> 10746450 | C3: 693000000 | D3: 560000000 | E3: 86625000 | F3: =C3-D3-E3 -> 46375000 | G3: =F3-B3 -> 35628550 | H3: =MAX(0,G3*0.25) -> 8907137.5 | I3: =G3-H3 -> 26721412 | J3: =I3+B3 -> 37467862 | K3: =K2+J3 -> -1.2253214e+08
A4: 2 | B4: =Assumptions!B2*0.06179 -> 10195350 | C4: 693000000 | D4: 560000000 | E4: 86625000 | F4: =C4-D4-E4 -> 46375000 | G4: =F4-B4 -> 36179650 | H4: =MAX(0,G4*0.25) -> 9044912.5 | I4: =G4-H4 -> 27134738 | J4: =I4+B4 -> 37330088 | K4: =K3+J4 -> -85202050
A5: 3 | B5: =Assumptions!B2*0.05901 -> 9736650 | C5: 693000000 | D5: 560000000 | E5: 86625000 | F5: =C5-D5-E5 -> 46375000 | G5: =F5-B5 -> 36638350 | H5: =MAX(0,G5*0.25) -> 9159587.5 | I5: =G5-H5 -> 27478762 | J5: =I5+B5 -> 37215412 | K5: =K4+J5 -> -47986638
A6: 4 | B6: =Assumptions!B2*0.05635 -> 9297750 | C6: 693000000 | D6: 560000000 | E6: 86625000 | F6: =C6-D6-E6 -> 46375000 | G6: =F6-B6 -> 37077250 | H6: =MAX(0,G6*0.25) -> 9269312.5 | I6: =G6-H6 -> 27807938 | J6: =I6+B6 -> 37105688 | K6: =K5+J6 -> -10880950
A7: 5 | B7: =Assumptions!B2*0.05376 -> 8870400 | C7: 693000000 | D7: 560000000 | E7: 86625000 | F7: =C7-D7-E7 -> 46375000 | G7: =F7-B7 -> 37504600 | H7: =MAX(0,G7*0.25) -> 9376150 | I7: =G7-H7 -> 28128450 | J7: =I7+B7 -> 36998850 | K7: =K6+J7 -> 26117900
A8: 6 | B8: =Assumptions!B2*0.05125 -> 8456250 | C8: 693000000 | D8: 560000000 | E8: 86625000 | F8: =C8-D8-E8 -> 46375000 | G8: =F8-B8 -> 37918750 | H8: =MAX(0,G8*0.25) -> 9479687.5 | I8: =G8-H8 -> 28439062 | J8: =I8+B8 -> 36895312 | K8: =K7+J8 -> 63013212
A9: 7 | B9: =Assumptions!B2*0.04881 -> 8053650 | C9: 693000000 | D9: 560000000 | E9: 86625000 | F9: =C9-D9-E9 -> 46375000 | G9: =F9-B9 -> 38321350 | H9: =MAX(0,G9*0.25) -> 9580337.5 | I9: =G9-H9 -> 28741012 | J9: =I9+B9 -> 36794662 | K9: =K8+J9 -> 99807875
A10: 8 | B10: =Assumptions!B2*0.04644 -> 7662600 | C10: 693000000 | D10: 560000000 | E10: 86625000 | F10: =C10-D10-E10 -> 46375000 | G10: =F10-B10 -> 38712400 | H10: =MAX(0,G10*0.25) -> 9678100 | I10: =G10-H10 -> 29034300 | J10: =I10+B10 -> 36696900 | K10: =K9+J10 -> 136504775
A11: 9 | B11: =Assumptions!B2*0.04413 -> 7281450 | C11: 693000000 | D11: 560000000 | E11: 86625000 | F11: =C11-D11-E11 -> 46375000 | G11: =F11-B11 -> 39093550 | H11: =MAX(0,G11*0.25) -> 9773387.5 | I11: =G11-H11 -> 29320162 | J11: =I11+B11 -> 36601612 | K11: =K10+J11 -> 1.7310639e+08
A12: 10 | B12: =Assumptions!B2*0.04189 -> 6911850 | C12: 693000000 | D12: 560000000 | E12: 86625000 | F12: =C12-D12-E12 -> 46375000 | G12: =F12-B12 -> 39463150 | H12: =MAX(0,G12*0.25) -> 9865787.5 | I12: =G12-H12 -> 29597362 | J12: =I12+B12 -> 36509212 | K12: =K11+J12 -> 209615600
A13: 11 | B13: =Assumptions!B2*0.03972 -> 6553800 | C13: 693000000 | D13: 560000000 | E13: 86625000 | F13: =C13-D13-E13 -> 46375000 | G13: =F13-B13 -> 39821200 | H13: =MAX(0,G13*0.25) -> 9955300 | I13: =G13-H13 -> 29865900 | J13: =I13+B13 -> 36419700 | K13: =K12+J13 -> 246035300
A14: 12 | B14: =Assumptions!B2*0.03762 -> 6207300 | C14: 693000000 | D14: 560000000 | E14: 86625000 | F14: =C14-D14-E14 -> 46375000 | G14: =F14-B14 -> 40167700 | H14: =MAX(0,G14*0.25) -> 10041925 | I14: =G14-H14 -> 30125775 | J14: =I14+B14 -> 36333075 | K14: =K13+J14 -> 282368375
A15: 13 | B15: =Assumptions!B2*0.03558 -> 5870700 | C15: 693000000 | D15: 560000000 | E15: 86625000 | F15: =C15-D15-E15 -> 46375000 | G15: =F15-B15 -> 40504300 | H15: =MAX(0,G15*0.25) -> 10126075 | I15: =G15-H15 -> 30378225 | J15: =I15+B15 -> 36248925 | K15: =K14+J15 -> 318617300
A16: 14 | B16: =Assumptions!B2*0.03361 -> 5545650 | C16: 693000000 | D16: 560000000 | E16: 86625000 | F16: =C16-D16-E16 -> 46375000 | G16: =F16-B16 -> 40829350 | H16: =MAX(0,G16*0.25) -> 10207338 | I16: =G16-H16 -> 30622012 | J16: =I16+B16 -> 36167662 | K16: =K15+J16 -> 3.5478496e+08
A17: 15 | B17: =Assumptions!B2*0.0317 -> 5230500 | C17: 693000000 | D17: 560000000 | E17: 86625000 | F17: =C17-D17-E17 -> 46375000 | G17: =F17-B17 -> 41144500 | H17: =MAX(0,G17*0.25) -> 10286125 | I17: =G17-H17 -> 30858375 | J17: =I17+B17 -> 36088875 | K17: =K16+J17 -> 3.9087384e+08
A18: 16 | B18: =Assumptions!B2*0.02986 -> 4926900 | C18: 693000000 | D18: 560000000 | E18: 86625000 | F18: =C18-D18-E18 -> 46375000 | G18: =F18-B18 -> 41448100 | H18: =MAX(0,G18*0.25) -> 10362025 | I18: =G18-H18 -> 31086075 | J18: =I18+B18 -> 36012975 | K18: =K17+J18 -> 4.2688681e+08
A19: 17 | B19: =Assumptions!B2*0.02808 -> 4633200 | C19: 693000000 | D19: 560000000 | E19: 86625000 | F19: =C19-D19-E19 -> 46375000 | G19: =F19-B19 -> 41741800 | H19: =MAX(0,G19*0.25) -> 10435450 | I19: =G19-H19 -> 31306350 | J19: =I19+B19 -> 35939550 | K19: =K18+J19 -> 4.6282636e+08
A20: 18 | B20: =Assumptions!B2*0.02637 -> 4351050 | C20: 693000000 | D20: 560000000 | E20: 86625000 | F20: =C20-D20-E20 -> 46375000 | G20: =F20-B20 -> 42023950 | H20: =MAX(0,G20*0.25) -> 10505988 | I20: =G20-H20 -> 31517962 | J20: =I20+B20 -> 35869012 | K20: =K19+J20 -> 498695375
A21: 19 | B21: =Assumptions!B2*0.02472 -> 4078800 | C21: 693000000 | D21: 560000000 | E21: 86625000 | F21: =C21-D21-E21 -> 46375000 | G21: =F21-B21 -> 42296200 | H21: =MAX(0,G21*0.25) -> 10574050 | I21: =G21-H21 -> 31722150 | J21: =I21+B21 -> 35800950 | K21: =K20+J21 -> 534496325
A22: 20 | B22: =Assumptions!B2*0.02314 -> 3818100 | C22: 693000000 | D22: 560000000 | E22: 86625000 | F22: =C22-D22-E22 -> 46375000 | G22: =F22-B22 -> 42556900 | H22: =MAX(0,G22*0.25) -> 10639225 | I22: =G22-H22 -> 31917675 | J22: =I22+B22 -> 35735775 | K22: =K21+J22 -> 570232100
A23: 21 | B23: =Assumptions!B2*0.02162 -> 3567300 | C23: 693000000 | D23: 560000000 | E23: 86625000 | F23: =C23-D23-E23 -> 46375000 | G23: =F23-B23 -> 42807700 | H23: =MAX(0,G23*0.25) -> 10701925 | I23: =G23-H23 -> 32105775 | J23: =I23+B23 -> 35673075 | K23: =K22+J23 -> 605905175
A24: 22 | B24: =Assumptions!B2*0.02017 -> 3328050 | C24: 693000000 | D24: 560000000 | E24: 86625000 | F24: =C24-D24-E24 -> 46375000 | G24: =F24-B24 -> 43046950 | H24: =MAX(0,G24*0.25) -> 10761738 | I24: =G24-H24 -> 32285212 | J24: =I24+B24 -> 35613262 | K24: =K23+J24 -> 6.4151844e+08
A25: 23 | B25: =Assumptions!B2*0.01878 -> 3098700 | C25: 693000000 | D25: 560000000 | E25: 86625000 | F25: =C25-D25-E25 -> 46375000 | G25: =F25-B25 -> 43276300 | H25: =MAX(0,G25*0.25) -> 10819075 | I25: =G25-H25 -> 32457225 | J25: =I25+B25 -> 35555925 | K25: =K24+J25 -> 6.7707436e+08
A26: 24 | B26: =Assumptions!B2*0.01746 -> 2880900 | C26: 693000000 | D26: 560000000 | E26: 86625000 | F26: =C26-D26-E26 -> 46375000 | G26: =F26-B26 -> 43494100 | H26: =MAX(0,G26*0.25) -> 10873525 | I26: =G26-H26 -> 32620575 | J26: =I26+B26 -> 35501475 | K26: =K25+J26 -> 7.1257584e+08
A27: 25 | B27: =Assumptions!B2*0.0162 -> 2673000 | C27: 693000000 | D27: 560000000 | E27: 86625000 | F27: =C27-D27-E27 -> 46375000 | G27: =F27-B27 -> 43702000 | H27: =MAX(0,G27*0.25) -> 10925500 | I27: =G27-H27 -> 32776500 | J27: =I27+B27 -> 35449500 | K27: =K26+J27 -> 7.4802534e+08
A28: 26 | B28: =Assumptions!B2*0.015 -> 2475000 | C28: 693000000 | D28: 560000000 | E28: 86625000 | F28: =C28-D28-E28 -> 46375000 | G28: =F28-B28 -> 43900000 | H28: =MAX(0,G28*0.25) -> 10975000 | I28: =G28-H28 -> 32925000 | J28: =I28+B28 -> 35400000 | K28: =K27+J28 -> 7.8342534e+08
A29: 27 | B29: =Assumptions!B2*0.01387 -> 2288550 | C29: 693000000 | D29: 560000000 | E29: 86625000 | F29: =C29-D29-E29 -> 46375000 | G29: =F29-B29 -> 44086450 | H29: =MAX(0,G29*0.25) -> 11021612 | I29: =G29-H29 -> 33064838 | J29: =I29+B29 -> 35353388 | K29: =K28+J29 -> 818778725
A30: 28 | B30: =Assumptions!B2*0.0128 -> 2112000 | C30: 693000000 | D30: 560000000 | E30: 86625000 | F30: =C30-D30-E30 -> 46375000 | G30: =F30-B30 -> 44263000 | H30: =MAX(0,G30*0.25) -> 11065750 | I30: =G30-H30 -> 33197250 | J30: =I30+B30 -> 35309250 | K30: =K29+J30 -> 854087975
A31: 29 | B31: =Assumptions!B2*0.0118 -> 1947000 | C31: 693000000 | D31: 560000000 | E31: 86625000 | F31: =C31-D31-E31 -> 46375000 | G31: =F31-B31 -> 44428000 | H31: =MAX(0,G31*0.25) -> 11107000 | I31: =G31-H31 -> 33321000 | J31: =I31+B31 -> 35268000 | K31: =K30+J31 -> 889355975
A32: 30 | B32: =Assumptions!B2*0.01086 -> 1791900 | C32: 693000000 | D32: 560000000 | E32: 86625000 | F32: =C32-D32-E32 -> 46375000 | G32: =F32-B32 -> 44583100 | H32: =MAX(0,G32*0.25) -> 11145775 | I32: =G32-H32 -> 33437325 | J32: =I32+B32 -> 35229225 | K32: =K31+J32 -> 924585200
